gcode2image.py
gcode2image-2.4.2.dist-info/entry_points.txt
gcode2image-2.4.2.dist-info/LICENSE
gcode2image-2.4.2.dist-info/WHEEL
gcode2image-2.4.2.dist-info/METADATA
gcode2image-2.4.2.dist-info/RECORD
