Metadata-Version: 2.1
Name: gcode2image
Version: 2.4.2
Summary: gcode2image: convert gcode to image.
Keywords: engraving,laser,image,laser engraving,PWM,gcode
Author-email: Johannes Noordanus <mailjohannes.mailnoordanus@gmail.com>
Requires-Python: >=3.7
Classifier: License :: OSI Approved :: MIT License
Requires-Dist: numpy >= 1.24.3
Requires-Dist: Pillow >= 9.5.0
Project-URL: Home, https://github.com/johannesnoordanus/gcode2image
